bibliobanana/__init__.py
bibliobanana/get.py
bibliobanana/io.py
bibliobanana/plot.py
bibliobanana-0.1.3.dist-info/DESCRIPTION.rst
bibliobanana-0.1.3.dist-info/METADATA
bibliobanana-0.1.3.dist-info/RECORD
bibliobanana-0.1.3.dist-info/WHEEL
bibliobanana-0.1.3.dist-info/metadata.json
bibliobanana-0.1.3.dist-info/top_level.txt
